src/__init__.py
src/main.py
src/amazon_connector/__init__.py
src/amazon_connector/amazon_order_connector.py
src/amazon_connector/base_connector.py
src/amazon_connector/types.py
src/captcha_solver/abstract_captcha_solver.py
src/captcha_solver/llm_captcha_solver.py
src/cli/__init__.py
src/cli/monarch_money_amazon_connector_cli.py
src/config/types.py
src/fsm/__init__.py
src/fsm/state_machine_implementation.py
src/fsm/states.py
src/monarch_connector/__init__.py
src/monarch_connector/api_types.py
src/monarch_connector/connector_types.py
src/monarch_connector/exceptions.py
src/monarch_connector/monarch.py
monarch_money_amazon_connector-2.2.0.dist-info/METADATA
monarch_money_amazon_connector-2.2.0.dist-info/WHEEL
monarch_money_amazon_connector-2.2.0.dist-info/entry_points.txt
monarch_money_amazon_connector-2.2.0.dist-info/licenses/LICENSE
monarch_money_amazon_connector-2.2.0.dist-info/RECORD
