Metadata-Version: 2.4
Name: monarch-money-amazon-connector
Version: 2.2.0
Summary: A simple package to automate the annotation of Amazon order transactions within Monarch Money with the purchased items.
Project-URL: Homepage, https://github.com/elsell/monarch-money-amazon-connector
Project-URL: Issues, https://github.com/elsell/monarch-money-amazon-connector/issues
Author-email: elsell <35787503+elsell@users.noreply.github.com>
License-File: LICENSE
Classifier: Development Status :: 4 - Beta
Classifier: Environment :: Console
Classifier: Framework :: Hatch
Classifier: License :: OSI Approved :: GNU General Public License v3 (GPLv3)
Classifier: Operating System :: OS Independent
Classifier: Programming Language :: Python :: 3
Requires-Python: >=3.11
Requires-Dist: loguru
Requires-Dist: monarchmoney==0.1.15
Requires-Dist: openai
Requires-Dist: pydantic-settings
Requires-Dist: pydantic==2.9.2
Requires-Dist: python-statemachine
Requires-Dist: selenium==4.25.0
Requires-Dist: tenacity==9.0.0
Requires-Dist: toml
Requires-Dist: webdriver-manager
Provides-Extra: build
Requires-Dist: twine; extra == 'build'
Provides-Extra: dev
Requires-Dist: pre-commit; extra == 'dev'
Requires-Dist: pytest; extra == 'dev'
Requires-Dist: pytest-asyncio; extra == 'dev'
Requires-Dist: pytest-sugar; extra == 'dev'
Requires-Dist: ruff; extra == 'dev'
Provides-Extra: test
Requires-Dist: pytest; extra == 'test'
Requires-Dist: pytest-asyncio; extra == 'test'
